tzafon_waypoint/__init__.py
tzafon_waypoint/_connection.py
tzafon_waypoint/client.py
tzafon_waypoint/exceptions.py
tzafon_waypoint/models.py
tzafon_waypoint-0.1.1.dist-info/METADATA
tzafon_waypoint-0.1.1.dist-info/WHEEL
tzafon_waypoint-0.1.1.dist-info/RECORD
