Metadata-Version: 2.4
Name: tzafon-waypoint
Version: 0.1.1
Summary: Waypoint – browser automation
License: MIT
Requires-Python: >=3.10
Requires-Dist: twine>=6.1.0
Requires-Dist: websockets>=15.0.1
